src/sequence_detector.v
module sequence_detector (
    input  wire clk,
    input  wire reset,
    input  wire bit_in,       
    input  wire bit_valid,    
    output reg  sequence_matched,
    output reg  [2:0] progress
);
    localparam [3:0]
        S_IDLE = 4'b0001, 
        S1     = 4'b0010, 
        S2     = 4'b0100, 
        S3     = 4'b1000; 

    reg [3:0] state, next_state;

    always @(posedge clk or posedge reset) begin
        if (reset) state <= S_IDLE;
        else state <= next_state;
    end

    // Translates the FSM state into the dot progress bar
    always @(*) begin
        case (state)
            S_IDLE: progress = 3'd0;
            S1:     progress = 3'd1;
            S2:     progress = 3'd2;
            S3:     progress = 3'd3;
            default: progress = 3'd0;
        endcase
    end

    always @(*) begin
        next_state = state;
        sequence_matched = 1'b0;
        
        if (bit_valid) begin
            case (state)
                S_IDLE: next_state = bit_in ? S1 : S_IDLE;
                S1:     next_state = bit_in ? S1 : S2; 
                S2:     next_state = bit_in ? S3 : S_IDLE; 
                S3: begin
                    if (bit_in) begin
                        sequence_matched = 1'b1; 
                        next_state = S1;         
                    end else begin
                        next_state = S2;         
                    end
                end
                default: next_state = S_IDLE;
            endcase
        end
    end
endmodule

src/tb_sequence_detector.v
`timescale 1ns / 1ps

module tb_sequence_detector;

    reg clk;
    reg reset;
    reg bit_in;
    reg bit_valid;

    wire sequence_matched;
    wire [2:0] progress;

    sequence_detector uut (
        .clk(clk),
        .reset(reset),
        .bit_in(bit_in),
        .bit_valid(bit_valid),
        .sequence_matched(sequence_matched),
        .progress(progress)
    );

    // Saat sinyali
    always #5 clk = ~clk;

    initial begin
        // 1. BAŞLANGIÇ VE RESET DURUMU
        clk = 0; reset = 1; bit_in = 0; bit_valid = 0;
        #10 reset = 0;

        // 2. NORMAL EŞLEŞME (1011)
        #10 bit_valid = 1; bit_in = 1; 
        #10 bit_in = 0;                
        #10 bit_in = 1;                
        #10 bit_in = 1; // -> BURADA sequence_matched = 1 OLMALI
        
        // 3. YANLIŞ DİZİLİM TESTİ (1010)
        #10 bit_in = 1; // S1
        #10 bit_in = 0; // S2
        #10 bit_in = 1; // S3
        #10 bit_in = 0; // Hatalı bit! S2'ye (10 durumuna) geri dönmeli.
        
        // 4. BİT GEÇERSİZ (PAUSE) TESTİ
        // Şu an sistem S2'de. bit_valid'i 0 yapıp 20ns bekliyoruz.
        #10 bit_valid = 0; bit_in = 1; // Bu '1'i görmezden gelmeli.
        #20; 
        
        // 5. PAUSE SONRASI DEVAM VE ÖRTÜŞME (OVERLAPPING) TESTİ
        #10 bit_valid = 1; bit_in = 1; // Kaldığı yerden (S2'den) devam edip S3'e geçmeli
        #10 bit_in = 1; // -> BURADA İKİNCİ sequence_matched = 1 OLMALI (1011 tamamlandı)
        
        // 6. DİZİ ORTASINDA ASENKRON RESET TESTİ
        #10 bit_in = 1; 
        #10 bit_in = 0; 
        #5  reset = 1;  // Dizi ortasında aniden reset geldi!
        #10 reset = 0;  // Sistem tamamen sıfırlanmış olmalı.

        #20 $finish;
    end

    initial begin
        $dumpfile("tb_sequence_detector.vcd");
        $dumpvars(0, tb_sequence_detector);
    end

endmodule

dump.vcd
$date
	Tue Apr 28 23:16:38 2026
$end
$version
	Icarus Verilog
$end
$timescale
	1ps
$end
$scope module tb_sequence_detector $end
$var wire 1 ! sequence_matched $end
$var wire 3 " progress [2:0] $end
$var reg 1 # bit_in $end
$var reg 1 $ bit_valid $end
$var reg 1 % clk $end
$var reg 1 & reset $end
$scope module uut $end
$var wire 1 # bit_in $end
$var wire 1 $ bit_valid $end
$var wire 1 % clk $end
$var wire 1 & reset $end
$var parameter 4 ' S1 $end
$var parameter 4 ( S2 $end
$var parameter 4 ) S3 $end
$var parameter 4 * S_IDLE $end
$var reg 4 + next_state [3:0] $end
$var reg 3 , progress [2:0] $end
$var reg 1 ! sequence_matched $end
$var reg 4 - state [3:0] $end
$upscope $end
$upscope $end
$enddefinitions $end
$comment Show the parameter values. $end
$dumpall
b1 *
b1000 )
b100 (
b10 '
$end
#0
$dumpvars
b1 -
b0 ,
b1 +
1&
0%
0$
0#
b0 "
0!
$end
#5000
1%
#10000
0%
0&
#15000
1%
#20000
b10 +
0%
1#
1$
#25000
b1 "
b1 ,
b10 -
1%
#30000
b100 +
0%
0#
#35000
b1 +
b10 "
b10 ,
b100 -
1%
#40000
b1000 +
0%
1#
#45000
b10 +
1!
b11 "
b11 ,
b1000 -
1%
#50000
0%
#55000
0!
b1 "
b1 ,
b10 -
1%
#60000
0%
#65000
1%
#70000
b100 +
0%
0#
#75000
b1 +
b10 "
b10 ,
b100 -
1%
#80000
b1000 +
0%
1#
#85000
b10 +
1!
b11 "
b11 ,
b1000 -
1%
#90000
0!
b100 +
0%
0#
#95000
b1 +
b10 "
b10 ,
b100 -
1%
#100000
b100 +
0%
1#
0$
#105000
1%
#110000
0%
#115000
1%
#120000
0%
#125000
1%
#130000
b1000 +
0%
1$
#135000
b10 +
1!
b11 "
b11 ,
b1000 -
1%
#140000
0%
#145000
0!
b1 "
b1 ,
b10 -
1%
#150000
0%
#155000
1%
#160000
b100 +
0%
0#
#165000
b1 +
b0 "
b0 ,
b1 -
1%
1&
#170000
0%
#175000
1%
0&
